{
  "ComponentIndexes": {
    "cmp_AdminButton": 6,
    "cmp_HomeButton": 7,
    "cmp_Navigation": 8
  },
  "ControlUniqueGuids": {},
  "ControlUniqueIds": {
    "AdminPanel": 26,
    "App": 1,
    "BookRoomWith": 41,
    "BookRoomWithout": 57,
    "Button1": 98,
    "Button2": 112,
    "Button3": 10,
    "Button3_1": 5,
    "cmp_AdminButton": 4,
    "cmp_AdminButton_1": 93,
    "cmp_HomeButton": 9,
    "cmp_HomeButton_1": 89,
    "cmp_HomeButton_2": 90,
    "cmp_HomeButton_3": 91,
    "cmp_Navigation": 14,
    "cmp_Navigation_1": 111,
    "cmp_Navigation_2": 56,
    "cmp_Navigation_3": 72,
    "cmp_Navigation_AdminPanel": 34,
    "Container_AdminPanelBackHome": 31,
    "Container_AdminPanelColorBanner": 30,
    "Container_AdminPanelLogIn": 35,
    "Container1": 16,
    "Container2": 79,
    "Container2_2": 105,
    "Container2_3": 47,
    "Container2_4": 63,
    "Container3": 15,
    "Container4": 87,
    "Container5": 88,
    "Container6": 11,
    "Container6_1": 6,
    "Container7": 92,
    "Container8": 53,
    "Container8_1": 69,
    "Dropdown1": 96,
    "Dropdown2": 97,
    "HeaderContainer1": 75,
    "HeaderContainer1_2": 101,
    "HeaderContainer1_3": 43,
    "HeaderContainer1_4": 59,
    "HeaderContainerAdminPanel": 28,
    "Home": 73,
    "Host": 3,
    "Image1": 86,
    "Image2": 76,
    "Image2_2": 102,
    "Image2_3": 44,
    "Image2_4": 60,
    "Image3": 54,
    "Image3_1": 70,
    "Image3_2": 32,
    "Image5": 85,
    "img_HomeButton": 12,
    "img_HomeButton_1": 8,
    "Label1": 77,
    "Label1_2": 103,
    "Label1_3": 94,
    "Label1_4": 45,
    "Label1_5": 61,
    "Label2": 36,
    "Label2_1": 37,
    "Label2_2": 39,
    "Label3": 55,
    "Label3_1": 71,
    "Label3_2": 33,
    "lbl_0": 17,
    "lbl_1": 18,
    "lbl_2": 19,
    "lbl_3": 20,
    "lbl_HomeButton": 13,
    "lbl_HomeButton_1": 7,
    "MainContainer1": 78,
    "MainContainer1_2": 104,
    "MainContainer1_3": 46,
    "MainContainer1_4": 62,
    "MainContainerAdminPanel": 29,
    "Rectangle2": 80,
    "Rectangle2_2": 106,
    "Rectangle2_3": 48,
    "Rectangle2_4": 64,
    "Rectangle3": 81,
    "Rectangle3_2": 107,
    "Rectangle3_3": 49,
    "Rectangle3_4": 65,
    "Rectangle4": 82,
    "Rectangle4_2": 108,
    "Rectangle4_3": 50,
    "Rectangle4_4": 66,
    "Rectangle5": 83,
    "Rectangle5_2": 109,
    "Rectangle5_3": 51,
    "Rectangle5_4": 67,
    "Rectangle6": 84,
    "Rectangle6_2": 110,
    "Rectangle6_3": 52,
    "Rectangle6_4": 68,
    "Screen1": 95,
    "ScreenContainer1": 74,
    "ScreenContainer1_2": 100,
    "ScreenContainer1_3": 42,
    "ScreenContainer1_4": 58,
    "ScreenContainerAdminPanel": 27,
    "shp_Divider": 25,
    "shp_Underline0": 21,
    "shp_Underline1": 22,
    "shp_Underline2": 23,
    "shp_Underline3": 24,
    "Template": 99,
    "TextInput1": 38,
    "TextInput2": 40
  },
  "FunctionParamsInvariantScripts": {},
  "FunctionParamsInvariantScriptsOnInstances": {},
  "HeaderLastSavedDateTimeUTC": "11/22/2023 16:59:24",
  "IsLegacyComponentAllowGlobalScopeCase": false,
  "LocalConnectionIDReferences": {},
  "LocalDatabaseReferencesAsEmpty": false,
  "LocalResourceFileNames": {
    "AdminSettings": "0001.svg",
    "Building": "0002.svg",
    "Calendar": "0003.svg",
    "CalendarCheck": "0004.svg",
    "HomeImage": "0005.png",
    "HomeImage_Mobile": "0006.png",
    "LeftArrow": "0007.svg",
    "Logo": "0008.png"
  },
  "LocalResourceRootPaths": {
    "AdminSettings": "https://docserverpwaprodwus.blob.core.windows.net/cbf6d958-d371-4750-b0a8-cea70930a463-1/resource/Assets0Images00001.svg?skoid=58690ece-ec83-4ce2-9ce8-883d4d6a54ee&sktid=975f013f-7f24-47e8-a7d3-abc4752bf346&skt=2023-11-22T16%3A57%3A44Z&ske=2023-11-23T17%3A12%3A44Z&sks=b&skv=2021-12-02&sv=2021-12-02&spr=https&se=2023-11-23T17%3A12%3A44Z&sr=b&sp=r&sig=nX7DgV%2BsbN0RFXNCssxBPYxqoT4%2FrcN4SMn7ccMPb5U%3D",
    "Building": "https://docserverpwaprodwus.blob.core.windows.net/cbf6d958-d371-4750-b0a8-cea70930a463-1/resource/Assets0Images00002.svg?skoid=58690ece-ec83-4ce2-9ce8-883d4d6a54ee&sktid=975f013f-7f24-47e8-a7d3-abc4752bf346&skt=2023-11-22T16%3A57%3A44Z&ske=2023-11-23T17%3A12%3A44Z&sks=b&skv=2021-12-02&sv=2021-12-02&spr=https&se=2023-11-23T17%3A12%3A44Z&sr=b&sp=r&sig=y80Y7TJRwhnK8At8phBPvL4XGApO63LYug36ESm33B8%3D",
    "Calendar": "https://docserverpwaprodwus.blob.core.windows.net/cbf6d958-d371-4750-b0a8-cea70930a463-1/resource/Assets0Images00003.svg?skoid=58690ece-ec83-4ce2-9ce8-883d4d6a54ee&sktid=975f013f-7f24-47e8-a7d3-abc4752bf346&skt=2023-11-22T16%3A57%3A44Z&ske=2023-11-23T17%3A12%3A44Z&sks=b&skv=2021-12-02&sv=2021-12-02&spr=https&se=2023-11-23T17%3A12%3A44Z&sr=b&sp=r&sig=It91ws%2BPMyF4J3A6mZmeypr6pAymvPbGwDVH%2BIm1mmI%3D",
    "CalendarCheck": "https://docserverpwaprodwus.blob.core.windows.net/cbf6d958-d371-4750-b0a8-cea70930a463-1/resource/Assets0Images00004.svg?skoid=58690ece-ec83-4ce2-9ce8-883d4d6a54ee&sktid=975f013f-7f24-47e8-a7d3-abc4752bf346&skt=2023-11-22T16%3A57%3A44Z&ske=2023-11-23T17%3A12%3A44Z&sks=b&skv=2021-12-02&sv=2021-12-02&spr=https&se=2023-11-23T17%3A12%3A44Z&sr=b&sp=r&sig=IkJeHzuKp2Webusv9E7umHqmcmv85cJQqbdJXeY1SJo%3D",
    "HomeImage": "https://docserverpwaprodwus.blob.core.windows.net/cbf6d958-d371-4750-b0a8-cea70930a463-1/resource/Assets0Images00005.png?skoid=58690ece-ec83-4ce2-9ce8-883d4d6a54ee&sktid=975f013f-7f24-47e8-a7d3-abc4752bf346&skt=2023-11-22T16%3A57%3A44Z&ske=2023-11-23T17%3A12%3A44Z&sks=b&skv=2021-12-02&sv=2021-12-02&spr=https&se=2023-11-23T17%3A12%3A44Z&sr=b&sp=r&sig=g9XIV%2FLrubd0Qabd3BFZKVS0w1iOeQjl3BuJeEkwrO0%3D",
    "HomeImage_Mobile": "https://docserverpwaprodwus.blob.core.windows.net/cbf6d958-d371-4750-b0a8-cea70930a463-1/resource/Assets0Images00006.png?skoid=58690ece-ec83-4ce2-9ce8-883d4d6a54ee&sktid=975f013f-7f24-47e8-a7d3-abc4752bf346&skt=2023-11-22T16%3A57%3A44Z&ske=2023-11-23T17%3A12%3A44Z&sks=b&skv=2021-12-02&sv=2021-12-02&spr=https&se=2023-11-23T17%3A12%3A44Z&sr=b&sp=r&sig=HEySt7pKyckdc4Gkqr%2BOuZOimmpEDzp54KERSlS%2Fp64%3D",
    "LeftArrow": "https://docserverpwaprodwus.blob.core.windows.net/cbf6d958-d371-4750-b0a8-cea70930a463-1/resource/Assets0Images00007.svg?skoid=58690ece-ec83-4ce2-9ce8-883d4d6a54ee&sktid=975f013f-7f24-47e8-a7d3-abc4752bf346&skt=2023-11-22T16%3A57%3A44Z&ske=2023-11-23T17%3A12%3A44Z&sks=b&skv=2021-12-02&sv=2021-12-02&spr=https&se=2023-11-23T17%3A12%3A44Z&sr=b&sp=r&sig=jQyafmE74RQAjKMjTm9Psy6WKi3kcfcw25xPGBNilC8%3D",
    "Logo": "https://docserverpwaprodwus.blob.core.windows.net/cbf6d958-d371-4750-b0a8-cea70930a463-1/resource/Assets0Images00008.png?skoid=58690ece-ec83-4ce2-9ce8-883d4d6a54ee&sktid=975f013f-7f24-47e8-a7d3-abc4752bf346&skt=2023-11-22T16%3A57%3A44Z&ske=2023-11-23T17%3A12%3A44Z&sks=b&skv=2021-12-02&sv=2021-12-02&spr=https&se=2023-11-23T17%3A12%3A44Z&sr=b&sp=r&sig=U1AwAxbXN%2BxOarwKSr1lyRTQ%2FL%2B1UFHyGB74czda8Qs%3D"
  },
  "OrderComponentMetadata": {
    "18e1011f6ac84211b3efb9fcb979ce45": 1,
    "39828aeba63b4331b468125c8119579f": 2,
    "86ab3854ab3545588a2cfdfa87fc0037": 0
  },
  "OrderComponentTemplate": {
    "18e1011f6ac84211b3efb9fcb979ce45": 1,
    "39828aeba63b4331b468125c8119579f": 2,
    "86ab3854ab3545588a2cfdfa87fc0037": 0
  },
  "OrderDataSource": {
    "col_Timing": 3,
    "colNavItems": 2,
    "CustomGallerySample": 0,
    "DropDownSample": 1
  },
  "OrderGroupControls": {},
  "OrderPcfTemplate": {},
  "OrderTemplate": {},
  "OrderXMLTemplate": {
    "button": 4,
    "dropdown": 6,
    "groupContainer": 0,
    "image": 1,
    "label": 2,
    "rectangle": 3,
    "text": 5
  },
  "OverridablePropertiesEntry": {
    "AdminPanel": {},
    "App": {},
    "BookRoomWith": {},
    "BookRoomWithout": {},
    "Button1": {},
    "Button2": {},
    "Button3": {},
    "Button3_1": {},
    "cmp_AdminButton": {},
    "cmp_AdminButton_1": {},
    "cmp_HomeButton": {},
    "cmp_HomeButton_1": {},
    "cmp_HomeButton_2": {},
    "cmp_HomeButton_3": {},
    "cmp_Navigation": {},
    "cmp_Navigation_1": {},
    "cmp_Navigation_2": {},
    "cmp_Navigation_3": {},
    "cmp_Navigation_AdminPanel": {},
    "Container_AdminPanelBackHome": {},
    "Container_AdminPanelColorBanner": {},
    "Container_AdminPanelLogIn": {},
    "Container1": {},
    "Container2": {},
    "Container2_2": {},
    "Container2_3": {},
    "Container2_4": {},
    "Container3": {},
    "Container4": {},
    "Container5": {},
    "Container6": {},
    "Container6_1": {},
    "Container7": {},
    "Container8": {},
    "Container8_1": {},
    "Dropdown1": {},
    "Dropdown2": {},
    "HeaderContainer1": {},
    "HeaderContainer1_2": {},
    "HeaderContainer1_3": {},
    "HeaderContainer1_4": {},
    "HeaderContainerAdminPanel": {},
    "Home": {},
    "Host": {},
    "Image1": {},
    "Image2": {},
    "Image2_2": {},
    "Image2_3": {},
    "Image2_4": {},
    "Image3": {},
    "Image3_1": {},
    "Image3_2": {},
    "Image5": {},
    "img_HomeButton": {},
    "img_HomeButton_1": {},
    "Label1": {},
    "Label1_2": {},
    "Label1_3": {},
    "Label1_4": {},
    "Label1_5": {},
    "Label2": {},
    "Label2_1": {},
    "Label2_2": {},
    "Label3": {},
    "Label3_1": {},
    "Label3_2": {},
    "lbl_0": {},
    "lbl_1": {},
    "lbl_2": {},
    "lbl_3": {},
    "lbl_HomeButton": {},
    "lbl_HomeButton_1": {},
    "MainContainer1": {},
    "MainContainer1_2": {},
    "MainContainer1_3": {},
    "MainContainer1_4": {},
    "MainContainerAdminPanel": {},
    "Rectangle2": {},
    "Rectangle2_2": {},
    "Rectangle2_3": {},
    "Rectangle2_4": {},
    "Rectangle3": {},
    "Rectangle3_2": {},
    "Rectangle3_3": {},
    "Rectangle3_4": {},
    "Rectangle4": {},
    "Rectangle4_2": {},
    "Rectangle4_3": {},
    "Rectangle4_4": {},
    "Rectangle5": {},
    "Rectangle5_2": {},
    "Rectangle5_3": {},
    "Rectangle5_4": {},
    "Rectangle6": {},
    "Rectangle6_2": {},
    "Rectangle6_3": {},
    "Rectangle6_4": {},
    "Screen1": {},
    "ScreenContainer1": {},
    "ScreenContainer1_2": {},
    "ScreenContainer1_3": {},
    "ScreenContainer1_4": {},
    "ScreenContainerAdminPanel": {},
    "shp_Divider": {},
    "shp_Underline0": {},
    "shp_Underline1": {},
    "shp_Underline2": {},
    "shp_Underline3": {},
    "Template": {},
    "TextInput1": {},
    "TextInput2": {}
  },
  "PCFDynamicSchemaForIRRetrievalEntry": {},
  "PCFTemplateEntry": {},
  "PublishOrderIndices": {
    "AdminPanel": 23,
    "App": 0,
    "BookRoomWith": 40,
    "BookRoomWithout": 56,
    "Button1": 97,
    "Button2": 0,
    "Button3": 7,
    "Button3_1": 2,
    "cmp_AdminButton": 1,
    "cmp_AdminButton_1": 93,
    "cmp_HomeButton": 6,
    "cmp_HomeButton_1": 90,
    "cmp_HomeButton_2": 91,
    "cmp_HomeButton_3": 92,
    "cmp_Navigation": 11,
    "cmp_Navigation_1": 105,
    "cmp_Navigation_2": 48,
    "cmp_Navigation_3": 64,
    "cmp_Navigation_AdminPanel": 29,
    "Container_AdminPanelBackHome": 28,
    "Container_AdminPanelColorBanner": 27,
    "Container_AdminPanelLogIn": 30,
    "Container1": 18,
    "Container2": 79,
    "Container2_2": 104,
    "Container2_3": 46,
    "Container2_4": 62,
    "Container3": 12,
    "Container4": 82,
    "Container5": 88,
    "Container6": 8,
    "Container6_1": 3,
    "Container7": 89,
    "Container8": 47,
    "Container8_1": 63,
    "Dropdown1": 95,
    "Dropdown2": 96,
    "HeaderContainer1": 75,
    "HeaderContainer1_2": 100,
    "HeaderContainer1_3": 42,
    "HeaderContainer1_4": 58,
    "HeaderContainerAdminPanel": 25,
    "Home": 72,
    "Host": 0,
    "Image1": 81,
    "Image2": 77,
    "Image2_2": 102,
    "Image2_3": 44,
    "Image2_4": 60,
    "Image3": 54,
    "Image3_1": 70,
    "Image3_2": 31,
    "Image5": 80,
    "img_HomeButton": 9,
    "img_HomeButton_1": 5,
    "Label1": 78,
    "Label1_2": 103,
    "Label1_3": 74,
    "Label1_4": 45,
    "Label1_5": 61,
    "Label2": 33,
    "Label2_1": 34,
    "Label2_2": 36,
    "Label3": 55,
    "Label3_1": 71,
    "Label3_2": 32,
    "lbl_0": 19,
    "lbl_1": 20,
    "lbl_2": 21,
    "lbl_3": 22,
    "lbl_HomeButton": 10,
    "lbl_HomeButton_1": 4,
    "MainContainer1": 76,
    "MainContainer1_2": 101,
    "MainContainer1_3": 43,
    "MainContainer1_4": 59,
    "MainContainerAdminPanel": 26,
    "Rectangle2": 83,
    "Rectangle2_2": 106,
    "Rectangle2_3": 49,
    "Rectangle2_4": 65,
    "Rectangle3": 84,
    "Rectangle3_2": 107,
    "Rectangle3_3": 50,
    "Rectangle3_4": 66,
    "Rectangle4": 85,
    "Rectangle4_2": 108,
    "Rectangle4_3": 51,
    "Rectangle4_4": 67,
    "Rectangle5": 86,
    "Rectangle5_2": 109,
    "Rectangle5_3": 52,
    "Rectangle5_4": 68,
    "Rectangle6": 87,
    "Rectangle6_2": 110,
    "Rectangle6_3": 53,
    "Rectangle6_4": 69,
    "Screen1": 94,
    "ScreenContainer1": 73,
    "ScreenContainer1_2": 99,
    "ScreenContainer1_3": 41,
    "ScreenContainer1_4": 57,
    "ScreenContainerAdminPanel": 24,
    "shp_Divider": 17,
    "shp_Underline0": 13,
    "shp_Underline1": 14,
    "shp_Underline2": 15,
    "shp_Underline3": 16,
    "Template": 98,
    "TextInput1": 35,
    "TextInput2": 37
  },
  "ResourcesJsonIndices": {
    "Image-AdminSettings": 1,
    "Image-Building": 2,
    "Image-Calendar": 3,
    "Image-CalendarCheck": 4,
    "Image-HomeImage": 5,
    "Image-HomeImage_Mobile": 6,
    "Image-LeftArrow": 7,
    "Image-Logo": 8,
    "Image-SampleImage": 0
  },
  "RuleScreenIdWithoutScreen": {},
  "TemplateVersions": {},
  "VolatileProperties": {
    "AnalysisLoadTime": 0.2462588,
    "ControlCount": {
      "18e1011f6ac84211b3efb9fcb979ce45": 4,
      "39828aeba63b4331b468125c8119579f": 5,
      "86ab3854ab3545588a2cfdfa87fc0037": 2,
      "button": 3,
      "dropdown": 2,
      "groupContainer": 31,
      "image": 11,
      "label": 17,
      "rectangle": 25,
      "screen": 6,
      "text": 2
    },
    "DeserializationLoadTime": 0.7925668
  },
  "WasLocalDatabaseReferencesEmpty": true
}